Metadata-Version: 2.1
Name: llab-omero-iviewer
Version: 0.11.4.dev0
Summary: A Python plugin for OMERO.web on Athena
Home-page: https://github.com/barrettMCW/omero-iviewerLLAB/
Author: The Open Microscopy Team
Author-email: ome-devel@lists.openmicroscopy.org.uk
License: AGPL-3.0
Download-URL: https://github.com/barrettMCW/omero-iviewerLLAB/archive/v0.11.4dev0.tar.gz
Keywords: OMERO.web,plugin
Platform: UNKNOWN
Classifier: Development Status :: 5 - Production/Stable
Classifier: Environment :: Web Environment
Classifier: Framework :: Django
Classifier: Intended Audience :: End Users/Desktop
Classifier: Intended Audience :: Science/Research
Classifier: Natural Language :: English
Classifier: Operating System :: OS Independent
Classifier: Programming Language :: JavaScript
Classifier: Programming Language :: Python :: 3
Classifier: Topic :: Internet :: WWW/HTTP
Classifier: Topic :: Internet :: WWW/HTTP :: Dynamic Content
Classifier: Topic :: Internet :: WWW/HTTP :: WSGI
Classifier: Topic :: Scientific/Engineering :: Visualization
Classifier: Topic :: Software Development :: Libraries :: Application Frameworks
Classifier: Topic :: Text Processing :: Markup :: HTML
Requires-Python: >=3
License-File: LICENSE
Requires-Dist: omero-web (>=5.7.0)
